relationlist/__init__.py
relationlist/ver.py
relationlist-1.2.1.dist-info/LICENSE
relationlist-1.2.1.dist-info/METADATA
relationlist-1.2.1.dist-info/WHEEL
relationlist-1.2.1.dist-info/top_level.txt
relationlist-1.2.1.dist-info/RECORD
